rapid_redis/__init__.py
rapid_redis/cache.py
rapid_redis/datastructures/__init__.py
rapid_redis/datastructures/hash.py
rapid_redis/datastructures/lists.py
rapid_redis/datastructures/sets.py
rapid_redis/datastructures/strings.py
rapid_redis-0.1.1.dist-info/licenses/LICENSE
rapid_redis-0.1.1.dist-info/METADATA
rapid_redis-0.1.1.dist-info/WHEEL
rapid_redis-0.1.1.dist-info/top_level.txt
rapid_redis-0.1.1.dist-info/RECORD
