Metadata-Version: 2.4
Name: rapid-redis
Version: 0.1.1
Summary: A lightweight in-memory cache inspired by Redis (educational)
Home-page: https://github.com/AtharshKrishnamoorthy/RAPID-REDIS.git
Author: Atharsh K
Author-email: atharshkrishnamoorthy@gmail.com
License: MIT
Requires-Python: >=3.7
License-File: LICENSE
Dynamic: author
Dynamic: author-email
Dynamic: description
Dynamic: description-content-type
Dynamic: home-page
Dynamic: license
Dynamic: license-file
Dynamic: requires-python
Dynamic: summary
